{
  "name": "حيوانات",
  "pairs": [
    { "normal": "قطة", "odd": "نسر" },
    { "normal": "أسد", "odd": "سمكة" },
    { "normal": "حصان", "odd": "تمساح" },
    { "normal": "فيل", "odd": "ضفدع" },
    { "normal": "ذئب", "odd": "فرخ" },
    { "normal": "دب", "odd": "عنكبوت" },
    { "normal": "جمل", "odd": "سلحفاة" },
    { "normal": "عصفور", "odd": "ثعبان" },
    { "normal": "سمكة", "odd": "فأر" },
    { "normal": "دجاجة", "odd": "خفاشي" },
    { "normal": "قرد", "odd": "كنغر" },
    { "normal": "زرافة", "odd": "سمور" },
    { "normal": "فهد", "odd": "بجعة" },
    { "normal": "غزال", "odd": "قنفذ" },
    { "normal": "كلب", "odd": "كسلان" },
    { "normal": "أرنب", "odd": "سحلية" },
    { "normal": "ضأن", "odd": "حبار" },
    { "normal": "بقرة", "odd": "فرس النهر" },
    { "normal": "تمساح", "odd": "نعامة" },
    { "normal": "ببغاء", "odd": "يرقة" },
    { "normal": "ديك", "odd": "جراد" },
    { "normal": "بطة", "odd": "نملة" },
    { "normal": "حمار", "odd": "نحلة" },
    { "normal": "بغل", "odd": "برغوث" },
    { "normal": "جدي", "odd": "صرصار" },
    { "normal": "كبش", "odd": "ذبابة" },
    { "normal": "بقرة وحشية", "odd": "عقرب" },
    { "normal": "أيل", "odd": "عنكبوت سم" },
    { "normal": "خنزير", "odd": "دودة" },
    { "normal": "جاموس", "odd": "برص" },
    { "normal": "ثعلب", "odd": "ثعبان سام" },
    { "normal": "أسد جبلي", "odd": "فراشة" },
    { "normal": "نمر", "odd": "ضفدع سم" },
    { "normal": "فيل آسيوي", "odd": "خنفساء" },
    { "normal": "زرافة", "odd": "ديدان أرضية" },
    { "normal": "نعجة", "odd": "كاركاجو" },
    { "normal": "حمير", "odd": "الكوكيل" },
    { "normal": "جمل بحري", "odd": "كائنات صغيرة" },
    { "normal": "ثعلب قطبي", "odd": "ديك الديب" },
    { "normal": "قاقم", "odd": "سحالي" },
    { "normal": "إوز", "odd": "غاق" },
    { "normal": "حمام", "odd": "طائر الهدهد" },
    { "normal": "ببغاء كاكاو", "odd": "ببغاء أفريقي" },
    { "normal": "طائر النعامة", "odd": "ببغاء زرقاء" },
    { "normal": "محار", "odd": "جمبري" },
    { "normal": "سرطان بحر", "odd": "سلطعون" },
    { "normal": "أخطبوط", "odd": "قنديل البحر" },
    { "normal": "سمك السالمون", "odd": "سمك القد" },
    { "normal": "سمك التونة", "odd": "سمك الحدوق" },
    { "normal": "دلفين", "odd": "حوت أزرق" }
  ]
}
